{"__type__":"sp.SkeletonData","_name":"zi","_native":"raw-skeleton.json","_skeletonJson":{"skeleton":{"hash":"0FHmL3gzpPZ+sSUuiv2Fn97MDnE","spine":"3.6.53","width":596.49,"height":248.9,"images":"./textures/"},"bones":[{"name":"root"},{"name":"GOOD","parent":"root","rotation":-0.09},{"name":"GREAT","parent":"root"},{"name":"GREAT2","parent":"GREAT"},{"name":"bone","parent":"GREAT","scaleX":2,"scaleY":2},{"name":"good","parent":"GOOD"},{"name":"perfect","parent":"root"},{"name":"perfect1","parent":"perfect"},{"name":"perfect2","parent":"perfect1","scaleX":2,"scaleY":2},{"name":"xx1","parent":"perfect","x":222.44,"y":31.56},{"name":"xx2","parent":"perfect","x":-233.25,"y":-36.86},{"name":"xx3","parent":"perfect","x":-54.01,"y":103.24}],"slots":[{"name":"great","bone":"GREAT2","attachment":"great"},{"name":"good","bone":"good","attachment":"good"},{"name":"perfect1","bone":"perfect1","attachment":"perfect"},{"name":"p-1","bone":"perfect2","attachment":"p-1","blend":"additive"},{"name":"xx2","bone":"xx1","attachment":"xx2"},{"name":"xx3","bone":"xx2","attachment":"xx2"},{"name":"xx4","bone":"xx3","attachment":"xx2"},{"name":"g-1","bone":"bone","attachment":"g-1"}],"skins":{"default":{"g-1":{"g-1":{"width":206,"height":75},"g-2":{"width":206,"height":75},"g-3":{"width":206,"height":75},"g-4":{"width":206,"height":75},"g-6":{"width":206,"height":75},"g-7":{"width":206,"height":75},"g-9":{"width":206,"height":75},"g-10":{"width":206,"height":75}},"good":{"good":{"width":371,"height":118}},"great":{"great":{"width":402,"height":133}},"p-1":{"p-1":{"rotation":-0.09,"width":206,"height":92},"p-2":{"width":206,"height":92},"p-4":{"width":206,"height":92},"p-5":{"width":206,"height":92},"p-6":{"width":206,"height":92},"p-8":{"width":206,"height":92},"p-9":{"width":206,"height":92},"p-10":{"width":206,"height":92}},"perfect1":{"perfect":{"width":418,"height":184}},"xx2":{"xx2":{"width":128,"height":128}},"xx3":{"xx2":{"scaleX":1.2,"scaleY":1.2,"width":128,"height":128}},"xx4":{"xx2":{"scaleX":0.5,"scaleY":0.5,"width":128,"height":128}}}},"animations":{"good":{"slots":{"good":{"color":[{"time":0.6,"color":"ffffffff"},{"time":0.9,"color":"ffffff00"}]},"great":{"color":[{"time":0.6,"color":"ffffffff"},{"time":0.9,"color":"ffffff00"}]},"perfect1":{"color":[{"time":1,"color":"ffffffff"},{"time":1.4,"color":"ffffff00"}]}},"bones":{"GREAT2":{"translate":[{"time":0,"x":0,"y":-503.37},{"time":0.1667,"x":0,"y":0,"curve":"stepped"},{"time":0.6,"x":0,"y":0},{"time":0.9,"x":0,"y":731.5}],"scale":[{"time":0,"x":0,"y":0},{"time":0.1667,"x":1.7,"y":1.7},{"time":0.2667,"x":1,"y":1}]},"good":{"translate":[{"time":0,"x":0,"y":-503.37},{"time":0.1667,"x":0,"y":0,"curve":"stepped"},{"time":0.6,"x":0,"y":0},{"time":0.9,"x":0,"y":731.5}],"scale":[{"time":0,"x":0,"y":0},{"time":0.1667,"x":1.7,"y":1.7},{"time":0.2667,"x":1,"y":1}]},"GREAT":{"scale":[{"time":0,"x":0,"y":0}]},"perfect1":{"translate":[{"time":0,"x":0,"y":-503.37},{"time":0.1667,"x":0,"y":0,"curve":"stepped"},{"time":1,"x":0,"y":0},{"time":1.4,"x":0,"y":731.5}],"scale":[{"time":0,"x":0,"y":0},{"time":0.1667,"x":1.7,"y":1.7},{"time":0.2667,"x":1,"y":1}]},"perfect":{"scale":[{"time":0,"x":0,"y":0}]}}},"great":{"slots":{"g-1":{"attachment":[{"time":0,"name":null},{"time":0.3333,"name":"g-1"},{"time":0.3667,"name":"g-2"},{"time":0.4,"name":"g-3"},{"time":0.4333,"name":"g-4"},{"time":0.4667,"name":"g-6"},{"time":0.5,"name":"g-7"},{"time":0.5333,"name":"g-9"},{"time":0.5667,"name":"g-10"},{"time":0.6,"name":null}]},"good":{"color":[{"time":0.6,"color":"ffffffff"},{"time":0.9,"color":"ffffff00"}]},"great":{"color":[{"time":0.6667,"color":"ffffffff"},{"time":0.9667,"color":"ffffff00"}]},"perfect1":{"color":[{"time":1,"color":"ffffffff"},{"time":1.4,"color":"ffffff00"}]}},"bones":{"GREAT2":{"translate":[{"time":0,"x":0,"y":-503.37},{"time":0.1667,"x":0,"y":0,"curve":"stepped"},{"time":0.6667,"x":0,"y":0},{"time":0.9667,"x":0,"y":731.5}],"scale":[{"time":0,"x":0,"y":0},{"time":0.1667,"x":1.8,"y":1.8},{"time":0.2667,"x":1,"y":1}]},"good":{"translate":[{"time":0,"x":0,"y":-503.37},{"time":0.1667,"x":0,"y":0,"curve":"stepped"},{"time":0.6,"x":0,"y":0},{"time":0.9,"x":0,"y":731.5}],"scale":[{"time":0,"x":0,"y":0},{"time":0.1667,"x":1.7,"y":1.7},{"time":0.2667,"x":1,"y":1}]},"GOOD":{"scale":[{"time":0,"x":0,"y":0}]},"perfect1":{"translate":[{"time":0,"x":0,"y":-503.37},{"time":0.1667,"x":0,"y":0,"curve":"stepped"},{"time":1,"x":0,"y":0},{"time":1.4,"x":0,"y":731.5}],"scale":[{"time":0,"x":0,"y":0},{"time":0.1667,"x":1.7,"y":1.7},{"time":0.2667,"x":1,"y":1}]},"perfect":{"scale":[{"time":0,"x":0,"y":0}]}}},"perfect":{"slots":{"good":{"color":[{"time":0.6,"color":"ffffffff"},{"time":0.9,"color":"ffffff00"}]},"great":{"color":[{"time":0.6,"color":"ffffffff"},{"time":0.9,"color":"ffffff00"}]},"p-1":{"attachment":[{"time":0,"name":null},{"time":0.3,"name":"p-1"},{"time":0.3333,"name":"p-2"},{"time":0.3667,"name":"p-4"},{"time":0.4,"name":"p-5"},{"time":0.4333,"name":"p-6"},{"time":0.4667,"name":"p-8"},{"time":0.5,"name":"p-9"},{"time":0.5333,"name":"p-10"},{"time":0.5667,"name":null}]},"perfect1":{"color":[{"time":1,"color":"ffffffff"},{"time":1.4,"color":"ffffff00"}]},"xx2":{"color":[{"time":0.5667,"color":"ffffffff"},{"time":0.7333,"color":"ffffff00"}]},"xx3":{"color":[{"time":0.7,"color":"ffffffff"},{"time":0.8667,"color":"ffffff00"}]},"xx4":{"color":[{"time":0.7,"color":"ffffffff"},{"time":0.8667,"color":"ffffff00"}]}},"bones":{"GREAT2":{"translate":[{"time":0,"x":0,"y":-503.37},{"time":0.1667,"x":0,"y":0,"curve":"stepped"},{"time":0.6,"x":0,"y":0},{"time":0.9,"x":0,"y":731.5}],"scale":[{"time":0,"x":0,"y":0},{"time":0.1667,"x":1.7,"y":1.7},{"time":0.2667,"x":1,"y":1}]},"good":{"translate":[{"time":0,"x":0,"y":-503.37},{"time":0.1667,"x":0,"y":0,"curve":"stepped"},{"time":0.6,"x":0,"y":0},{"time":0.9,"x":0,"y":731.5}],"scale":[{"time":0,"x":0,"y":0},{"time":0.1667,"x":1.7,"y":1.7},{"time":0.2667,"x":1,"y":1}]},"GREAT":{"scale":[{"time":0,"x":0,"y":0}]},"perfect1":{"translate":[{"time":0,"x":0,"y":-503.37},{"time":0.1667,"x":0,"y":0,"curve":"stepped"},{"time":1,"x":0,"y":0},{"time":1.4,"x":0,"y":731.5}],"scale":[{"time":0,"x":0,"y":0},{"time":0.1667,"x":1.8,"y":1.8},{"time":0.2667,"x":1,"y":1}]},"GOOD":{"scale":[{"time":0,"x":0,"y":0}]},"xx1":{"scale":[{"time":0,"x":0,"y":0,"curve":"stepped"},{"time":0.1667,"x":0,"y":0},{"time":0.3,"x":1.7,"y":1.7},{"time":0.4333,"x":0.2,"y":0.2},{"time":0.5667,"x":1,"y":1},{"time":0.7333,"x":0,"y":0}]},"xx2":{"scale":[{"time":0,"x":0,"y":0,"curve":"stepped"},{"time":0.2,"x":0,"y":0},{"time":0.3667,"x":1.7,"y":1.7},{"time":0.5,"x":0.2,"y":0.2},{"time":0.7,"x":1,"y":1},{"time":0.8667,"x":0,"y":0}]},"xx3":{"scale":[{"time":0,"x":0,"y":0,"curve":"stepped"},{"time":0.1667,"x":0,"y":0},{"time":0.3667,"x":1.7,"y":1.7},{"time":0.5,"x":0.2,"y":0.2},{"time":0.7,"x":1,"y":1},{"time":0.8667,"x":0,"y":0}]}}}}},"_atlasText":"\r\nzi.png\r\nsize: 1024,1024\r\nformat: RGBA8888\r\nfilter: Linear,Linear\r\nrepeat: none\r\ng-1\r\n  rotate: true\r\n  xy: 321, 571\r\n  size: 50, 63\r\n  orig: 206, 75\r\n  offset: 2, 8\r\n  index: -1\r\ng-10\r\n  rotate: false\r\n  xy: 84, 426\r\n  size: 61, 59\r\n  orig: 206, 75\r\n  offset: 143, 4\r\n  index: -1\r\ng-2\r\n  rotate: true\r\n  xy: 84, 487\r\n  size: 72, 64\r\n  orig: 206, 75\r\n  offset: 2, 7\r\n  index: -1\r\ng-3\r\n  rotate: true\r\n  xy: 2, 183\r\n  size: 98, 64\r\n  orig: 206, 75\r\n  offset: 2, 7\r\n  index: -1\r\ng-4\r\n  rotate: false\r\n  xy: 253, 623\r\n  size: 123, 65\r\n  orig: 206, 75\r\n  offset: 2, 6\r\n  index: -1\r\ng-6\r\n  rotate: false\r\n  xy: 422, 832\r\n  size: 142, 57\r\n  orig: 206, 75\r\n  offset: 39, 6\r\n  index: -1\r\ng-7\r\n  rotate: true\r\n  xy: 2, 283\r\n  size: 137, 59\r\n  orig: 206, 75\r\n  offset: 65, 4\r\n  index: -1\r\ng-9\r\n  rotate: true\r\n  xy: 2, 2\r\n  size: 86, 59\r\n  orig: 206, 75\r\n  offset: 118, 4\r\n  index: -1\r\ngood\r\n  rotate: false\r\n  xy: 422, 891\r\n  size: 371, 118\r\n  orig: 371, 118\r\n  offset: 0, 0\r\n  index: -1\r\ngreat\r\n  rotate: false\r\n  xy: 2, 690\r\n  size: 402, 133\r\n  orig: 402, 133\r\n  offset: 0, 0\r\n  index: -1\r\np-1\r\n  rotate: false\r\n  xy: 2, 90\r\n  size: 56, 91\r\n  orig: 206, 92\r\n  offset: 0, 1\r\n  index: -1\r\np-10\r\n  rotate: false\r\n  xy: 253, 567\r\n  size: 66, 54\r\n  orig: 206, 92\r\n  offset: 140, 2\r\n  index: -1\r\np-2\r\n  rotate: false\r\n  xy: 928, 917\r\n  size: 69, 92\r\n  orig: 206, 92\r\n  offset: 0, 0\r\n  index: -1\r\np-4\r\n  rotate: false\r\n  xy: 131, 596\r\n  size: 120, 92\r\n  orig: 206, 92\r\n  offset: 0, 0\r\n  index: -1\r\np-5\r\n  rotate: false\r\n  xy: 795, 917\r\n  size: 131, 92\r\n  orig: 206, 92\r\n  offset: 14, 0\r\n  index: -1\r\np-6\r\n  rotate: true\r\n  xy: 2, 422\r\n  size: 137, 80\r\n  orig: 206, 92\r\n  offset: 35, 2\r\n  index: -1\r\np-8\r\n  rotate: false\r\n  xy: 566, 835\r\n  size: 119, 54\r\n  orig: 206, 92\r\n  offset: 87, 2\r\n  index: -1\r\np-9\r\n  rotate: false\r\n  xy: 687, 835\r\n  size: 93, 54\r\n  orig: 206, 92\r\n  offset: 113, 2\r\n  index: -1\r\nperfect\r\n  rotate: false\r\n  xy: 2, 825\r\n  size: 418, 184\r\n  orig: 418, 184\r\n  offset: 0, 0\r\n  index: -1\r\nxx2\r\n  rotate: false\r\n  xy: 2, 561\r\n  size: 127, 127\r\n  orig: 128, 128\r\n  offset: 1, 1\r\n  index: -1\r\n","textures":[{"__uuid__":"3blyxUB7tP8rv0P2XwHXPw"}],"textureNames":["zi.png"]}